odoo8_addon_base_ubl_payment-8.0.1.0.0.99.dev6-nspkg.pth
odoo_addons/base_ubl_payment/README.rst
odoo_addons/base_ubl_payment/__init__.py
odoo_addons/base_ubl_payment/__openerp__.py
odoo_addons/base_ubl_payment/i18n/base_ubl_payment.pot
odoo_addons/base_ubl_payment/models/__init__.py
odoo_addons/base_ubl_payment/models/ubl.py
odoo_addons/base_ubl_payment/static/description/icon.png
odoo8_addon_base_ubl_payment-8.0.1.0.0.99.dev6.dist-info/METADATA
odoo8_addon_base_ubl_payment-8.0.1.0.0.99.dev6.dist-info/WHEEL
odoo8_addon_base_ubl_payment-8.0.1.0.0.99.dev6.dist-info/namespace_packages.txt
odoo8_addon_base_ubl_payment-8.0.1.0.0.99.dev6.dist-info/top_level.txt
odoo8_addon_base_ubl_payment-8.0.1.0.0.99.dev6.dist-info/RECORD
